setup.py
bnog_distributions/Binomialdistribution.py
bnog_distributions/Gaussiandistribution.py
bnog_distributions/Generaldistribution.py
bnog_distributions/__init__.py
bnog_distributions.egg-info/PKG-INFO
bnog_distributions.egg-info/SOURCES.txt
bnog_distributions.egg-info/dependency_links.txt
bnog_distributions.egg-info/not-zip-safe
bnog_distributions.egg-info/top_level.txt